<DATA flag="ufunc">

  <USED_FUNCTIONS name='ABS_VALUEi' type='XML'>
    <USED_FUNCTION>absolute_valuei</USED_FUNCTION>
  </USED_FUNCTIONS>

  <USED_FUNCTIONS name='BITCLEAR' type='XML'>
    <USED_FUNCTION>bit_clear_32</USED_FUNCTION>
    <USED_FUNCTION>bit_clear_16</USED_FUNCTION>
    <USED_FUNCTION>bit_clear_8</USED_FUNCTION>
  </USED_FUNCTIONS>

  <USED_FUNCTIONS name='BITSET' type='XML'>
    <USED_FUNCTION>bit_set_32</USED_FUNCTION>
    <USED_FUNCTION>bit_set_16</USED_FUNCTION>
    <USED_FUNCTION>bit_set_8</USED_FUNCTION>
  </USED_FUNCTIONS>

  <USED_FUNCTIONS name='CONVERT' type='XML'>
    <USED_FUNCTION>convert</USED_FUNCTION>
  </USED_FUNCTIONS>

  <USED_FUNCTIONS name='CUMSUM' type='XML'>
    <USED_FUNCTION>cumsum_m</USED_FUNCTION>
    <USED_FUNCTION>cumsum_r</USED_FUNCTION>
    <USED_FUNCTION>cumsum_c</USED_FUNCTION>
    <USED_FUNCTION>cumsumz_m</USED_FUNCTION>
    <USED_FUNCTION>cumsumz_r</USED_FUNCTION>
    <USED_FUNCTION>cumsumz_c</USED_FUNCTION>
  </USED_FUNCTIONS>

  <USED_FUNCTIONS name='EXTRACT' type='XML'>
    <USED_FUNCTION>extract</USED_FUNCTION>,
    <USED_FUNCTION>extractz</USED_FUNCTION>
  </USED_FUNCTIONS>

  <USED_FUNCTIONS name='EXTRACTBITS' type='XML'>
    <USED_FUNCTION>extract_bit_32_UH0</USED_FUNCTION>
    <USED_FUNCTION>extract_bit_32_UH1</USED_FUNCTION>
    <USED_FUNCTION>extract_bit_u32_UH1</USED_FUNCTION>
    <USED_FUNCTION>extract_bit_32_LH</USED_FUNCTION>
    <USED_FUNCTION>extract_bit_32_MSB0</USED_FUNCTION>
    <USED_FUNCTION>extract_bit_32_MSB1</USED_FUNCTION>
    <USED_FUNCTION>extract_bit_u32_MSB1</USED_FUNCTION>
    <USED_FUNCTION>extract_bit_32_LSB</USED_FUNCTION>
    <USED_FUNCTION>extract_bit_32_RB0</USED_FUNCTION>
    <USED_FUNCTION>extract_bit_32_RB1</USED_FUNCTION>
    <USED_FUNCTION>extract_bit_u32_RB1</USED_FUNCTION>
    <USED_FUNCTION>extract_bit_16_UH0</USED_FUNCTION>
    <USED_FUNCTION>extract_bit_16_UH1</USED_FUNCTION>
    <USED_FUNCTION>extract_bit_u16_UH1</USED_FUNCTION>
    <USED_FUNCTION>extract_bit_16_LH</USED_FUNCTION>
    <USED_FUNCTION>extract_bit_16_MSB0</USED_FUNCTION>
    <USED_FUNCTION>extract_bit_16_MSB1</USED_FUNCTION>
    <USED_FUNCTION>extract_bit_u16_MSB1</USED_FUNCTION>
    <USED_FUNCTION>extract_bit_16_LSB</USED_FUNCTION>
    <USED_FUNCTION>extract_bit_16_RB0</USED_FUNCTION>
    <USED_FUNCTION>extract_bit_16_RB1</USED_FUNCTION>
    <USED_FUNCTION>extract_bit_u16_RB1</USED_FUNCTION>
    <USED_FUNCTION>extract_bit_8_UH0</USED_FUNCTION>
    <USED_FUNCTION>extract_bit_8_UH1</USED_FUNCTION>
    <USED_FUNCTION>extract_bit_u8_UH1</USED_FUNCTION>
    <USED_FUNCTION>extract_bit_8_LH</USED_FUNCTION>
    <USED_FUNCTION>extract_bit_8_MSB0</USED_FUNCTION>
    <USED_FUNCTION>extract_bit_8_MSB1</USED_FUNCTION>
    <USED_FUNCTION>extract_bit_u8_MSB1</USED_FUNCTION>
    <USED_FUNCTION>extract_bit_8_LSB</USED_FUNCTION>
    <USED_FUNCTION>extract_bit_8_RB0</USED_FUNCTION>
    <USED_FUNCTION>extract_bit_8_RB1</USED_FUNCTION>
    <USED_FUNCTION>extract_bit_u8_RB1</USED_FUNCTION>

  </USED_FUNCTIONS>


  <USED_FUNCTIONS name='EXTTRI' type='XML'>
    <USED_FUNCTION>exttril</USED_FUNCTION>
    <USED_FUNCTION>exttriu</USED_FUNCTION>
    <USED_FUNCTION>extdiag</USED_FUNCTION>
    <USED_FUNCTION>exttrilz</USED_FUNCTION>
    <USED_FUNCTION>exttriuz</USED_FUNCTION>
    <USED_FUNCTION>extdiagz</USED_FUNCTION>
  </USED_FUNCTIONS>

  <USED_FUNCTIONS name='GAINBLK' type='XML'>
    <USED_FUNCTION>gainblk</USED_FUNCTION>
    <USED_FUNCTION>gainblk_i32n</USED_FUNCTION>
    <USED_FUNCTION>gainblk_i16n</USED_FUNCTION>
    <USED_FUNCTION>gainblk_i8n</USED_FUNCTION>
    <USED_FUNCTION>gainblk_ui32n</USED_FUNCTION>
    <USED_FUNCTION>gainblk_ui16n</USED_FUNCTION>
    <USED_FUNCTION>gainblk_ui8n</USED_FUNCTION>
    <USED_FUNCTION>gainblk_i32s</USED_FUNCTION>
    <USED_FUNCTION>gainblk_i16s</USED_FUNCTION>
    <USED_FUNCTION>gainblk_i8s</USED_FUNCTION>
    <USED_FUNCTION>gainblk_ui32s</USED_FUNCTION>
    <USED_FUNCTION>gainblk_ui16s</USED_FUNCTION>
    <USED_FUNCTION>gainblk_ui8s</USED_FUNCTION>
    <USED_FUNCTION>gainblk_i32e</USED_FUNCTION>
    <USED_FUNCTION>gainblk_i16e</USED_FUNCTION>
    <USED_FUNCTION>gainblk_i8e</USED_FUNCTION>
    <USED_FUNCTION>gainblk_ui32e</USED_FUNCTION>
    <USED_FUNCTION>gainblk_ui16e</USED_FUNCTION>
    <USED_FUNCTION>gainblk_ui8e</USED_FUNCTION>
  </USED_FUNCTIONS>

  <USED_FUNCTIONS name='Ground_g' type='XML'>
    <USED_FUNCTION>cstblk4_m</USED_FUNCTION>
  </USED_FUNCTIONS>

  <USED_FUNCTIONS name='INTEGRAL_m' type='XML'>
    <USED_FUNCTION>integral_func</USED_FUNCTION>
    <USED_FUNCTION>integralz_func</USED_FUNCTION>
  </USED_FUNCTIONS>

  <USED_FUNCTIONS name='INTMUL' type='XML'>
    <USED_FUNCTION>matmul_i32n</USED_FUNCTION>
    <USED_FUNCTION>matmul_i16n</USED_FUNCTION>
    <USED_FUNCTION>matmul_i8n</USED_FUNCTION>
    <USED_FUNCTION>matmul_ui32n</USED_FUNCTION>
    <USED_FUNCTION>matmul_ui16n</USED_FUNCTION>
    <USED_FUNCTION>matmul_ui8n</USED_FUNCTION>
    <USED_FUNCTION>matmul_i32s</USED_FUNCTION>
    <USED_FUNCTION>matmul_i16s</USED_FUNCTION>
    <USED_FUNCTION>matmul_i8s</USED_FUNCTION>
    <USED_FUNCTION>matmul_ui32s</USED_FUNCTION>
    <USED_FUNCTION>matmul_ui16s</USED_FUNCTION>
    <USED_FUNCTION>matmul_ui8s</USED_FUNCTION>
    <USED_FUNCTION>matmul_i32e</USED_FUNCTION>
    <USED_FUNCTION>matmul_i16e</USED_FUNCTION>
    <USED_FUNCTION>matmul_i8e</USED_FUNCTION>
    <USED_FUNCTION>matmul_ui32e</USED_FUNCTION>
    <USED_FUNCTION>matmul_ui16e</USED_FUNCTION>
    <USED_FUNCTION>matmul_ui8e</USED_FUNCTION>
  </USED_FUNCTIONS>

  <USED_FUNCTIONS name='LOGIC' type='XML'>
    <USED_FUNCTION>logic.c</USED_FUNCTION>
  </USED_FUNCTIONS>

  <USED_FUNCTIONS name='LOGICAL_OP' type='XML'>
    <USED_FUNCTION>logicalop</USED_FUNCTION>
    <USED_FUNCTION>logicalop_i32</USED_FUNCTION>
    <USED_FUNCTION>logicalop_i16</USED_FUNCTION>
    <USED_FUNCTION>logicalop_i8</USED_FUNCTION>
    <USED_FUNCTION>logicalop_ui32</USED_FUNCTION>
    <USED_FUNCTION>logicalop_ui16</USED_FUNCTION>
    <USED_FUNCTION>logicalop_ui8</USED_FUNCTION>
  </USED_FUNCTIONS>


  <USED_FUNCTIONS name='MATBKSL' type='XML'>
    <USED_FUNCTION>mat_bksl</USED_FUNCTION>
    <USED_FUNCTION>matz_bksl</USED_FUNCTION>
  </USED_FUNCTIONS>

  <USED_FUNCTIONS name='MATCATH' type='XML'>
    <USED_FUNCTION>mat_cath</USED_FUNCTION>,
    <USED_FUNCTION>matz_cath</USED_FUNCTION>
  </USED_FUNCTIONS>

  <USED_FUNCTIONS name='MATCATV' type='XML'>
    <USED_FUNCTION>mat_catv</USED_FUNCTION>,
    <USED_FUNCTION>matz_catv</USED_FUNCTION>
  </USED_FUNCTIONS>

  <USED_FUNCTIONS name='MATDET' type='XML'>
    <USED_FUNCTION>mat_det</USED_FUNCTION>,
    <USED_FUNCTION>matz_det</USED_FUNCTION>
  </USED_FUNCTIONS>

  <USED_FUNCTIONS name='MATDIAG' type='XML'>
    <USED_FUNCTION>mat_diag</USED_FUNCTION>,
    <USED_FUNCTION>matz_diag</USED_FUNCTION>
  </USED_FUNCTIONS>

  <USED_FUNCTIONS name='MATDIV' type='XML'>
    <USED_FUNCTION>mat_div</USED_FUNCTION>,
    <USED_FUNCTION>matz_div</USED_FUNCTION>
  </USED_FUNCTIONS>

  <USED_FUNCTIONS name='MATEIG' type='XML'>
    <USED_FUNCTION>mat_vps</USED_FUNCTION>,
    <USED_FUNCTION>mat_vpv</USED_FUNCTION>,
    <USED_FUNCTION>matz_vps</USED_FUNCTION>,
    <USED_FUNCTION>matz_vpv</USED_FUNCTION>
  </USED_FUNCTIONS>

  <USED_FUNCTIONS name='MATEXPM' type='XML'>
    <USED_FUNCTION>mat_expm</USED_FUNCTION>,
    <USED_FUNCTION>matz_expm</USED_FUNCTION>
  </USED_FUNCTIONS>

  <USED_FUNCTIONS name='MATINV' type='XML'>
    <USED_FUNCTION>mat_inv</USED_FUNCTION>,
    <USED_FUNCTION>matz_inv</USED_FUNCTION>
  </USED_FUNCTIONS>

  <USED_FUNCTIONS name='MATLU' type='XML'>
    <USED_FUNCTION>mat_lu</USED_FUNCTION>,
    <USED_FUNCTION>matz_lu</USED_FUNCTION>
  </USED_FUNCTIONS>

  <USED_FUNCTIONS name='MATMAGPHI' type='XML'>
    <USED_FUNCTION>matz_abs</USED_FUNCTION>,
    <USED_FUNCTION>matz_absc</USED_FUNCTION>
  </USED_FUNCTIONS>

  <USED_FUNCTIONS name='MATMUL' type='XML'>
    <USED_FUNCTION>matmul_m</USED_FUNCTION>
    <USED_FUNCTION>matzmul_m</USED_FUNCTION>
    <USED_FUNCTION>matmul2_m</USED_FUNCTION>
    <USED_FUNCTION>matzmul2_m</USED_FUNCTION>
  </USED_FUNCTIONS>

  <USED_FUNCTIONS name='MATPINV' type='XML'>
    <USED_FUNCTION>mat_pinv</USED_FUNCTION>,
    <USED_FUNCTION>matz_pinv</USED_FUNCTION>
  </USED_FUNCTIONS>

  <USED_FUNCTIONS name='MATRESH' type='XML'>
    <USED_FUNCTION>mat_reshape</USED_FUNCTION>,
    <USED_FUNCTION>matz_reshape</USED_FUNCTION>
  </USED_FUNCTIONS>

  <USED_FUNCTIONS name='MATSING' type='XML'>
    <USED_FUNCTION>mat_sing</USED_FUNCTION>,
    <USED_FUNCTION>mat_svd</USED_FUNCTION>,
    <USED_FUNCTION>matz_sing</USED_FUNCTION>,
    <USED_FUNCTION>matz_svd</USED_FUNCTION>
  </USED_FUNCTIONS>

  <USED_FUNCTIONS name='MATSUM' type='XML'>
    <USED_FUNCTION>mat_sum</USED_FUNCTION>
    <USED_FUNCTION>mat_suml</USED_FUNCTION>
    <USED_FUNCTION>mat_sumc</USED_FUNCTION>
    <USED_FUNCTION>matz_sum</USED_FUNCTION>
    <USED_FUNCTION>matz_suml</USED_FUNCTION>
    <USED_FUNCTION>matz_sumc</USED_FUNCTION>
  </USED_FUNCTIONS>

  <USED_FUNCTIONS name='MATTRAN' type='XML'>
    <USED_FUNCTION>mattran_m.c</USED_FUNCTION>,
    <USED_FUNCTION>matztran_m.c</USED_FUNCTION>
  </USED_FUNCTIONS>

  <USED_FUNCTIONS name='MATZCONJ' type='XML'>
    <USED_FUNCTION>matz_conj.c</USED_FUNCTION>
  </USED_FUNCTIONS>

  <USED_FUNCTIONS name='MATZREIM' type='XML'>
    <USED_FUNCTION>matz_reim.c</USED_FUNCTION>,
    <USED_FUNCTION>matz_reimc.c</USED_FUNCTION>
  </USED_FUNCTIONS>

  <USED_FUNCTIONS name='QUANT_f' type='XML'>
    <USED_FUNCTION>qzrnd</USED_FUNCTION>
    <USED_FUNCTION>qztrn</USED_FUNCTION>
    <USED_FUNCTION>qzflr</USED_FUNCTION>
    <USED_FUNCTION>qzcel</USED_FUNCTION>
  </USED_FUNCTIONS>

  <USED_FUNCTIONS name='RAND_m' type='XML'>
    <USED_FUNCTION>rndblk_m</USED_FUNCTION>
    <USED_FUNCTION>rndblkz_m</USED_FUNCTION>
  </USED_FUNCTIONS>

  <USED_FUNCTIONS name='REGISTER' type='XML'>
    <USED_FUNCTION>delay4_i32</USED_FUNCTION>
    <USED_FUNCTION>delay4_i16</USED_FUNCTION>
    <USED_FUNCTION>delay4_i8</USED_FUNCTION>
    <USED_FUNCTION>delay4_ui32</USED_FUNCTION>
    <USED_FUNCTION>delay4_ui16</USED_FUNCTION>
    <USED_FUNCTION>delay4_ui8</USED_FUNCTION>
  </USED_FUNCTIONS>

  <USED_FUNCTIONS name='RELATIONALOP' type='XML'>
    <USED_FUNCTION>relational_op</USED_FUNCTION>
    <USED_FUNCTION>relational_op_i32</USED_FUNCTION>
    <USED_FUNCTION>relational_op_i16</USED_FUNCTION>
    <USED_FUNCTION>relational_op_i8</USED_FUNCTION>
    <USED_FUNCTION>relational_op_ui32</USED_FUNCTION>
    <USED_FUNCTION>relational_op_ui16</USED_FUNCTION>
    <USED_FUNCTION>relational_op_ui8</USED_FUNCTION>
  </USED_FUNCTIONS>


  <USED_FUNCTIONS name='RICC' type='XML'>
    <USED_FUNCTION>ricc_m.c</USED_FUNCTION>
  </USED_FUNCTIONS>

  <USED_FUNCTIONS name='ROOTCOEF' type='XML'>
    <USED_FUNCTION>root_coef</USED_FUNCTION>
    <USED_FUNCTION>rootz_coef</USED_FUNCTION>
  </USED_FUNCTIONS>

  <USED_FUNCTIONS name='SHIFT' type='XML'>
    <USED_FUNCTION>shift_32_LA</USED_FUNCTION>
    <USED_FUNCTION>shift_32_LC</USED_FUNCTION>
    <USED_FUNCTION>shift_32_RA</USED_FUNCTION>
    <USED_FUNCTION>shift_u32_RA</USED_FUNCTION>
    <USED_FUNCTION>shift_32_RC</USED_FUNCTION>
    <USED_FUNCTION>shift_16_LA</USED_FUNCTION>
    <USED_FUNCTION>shift_16_LC</USED_FUNCTION>
    <USED_FUNCTION>shift_16_RA</USED_FUNCTION>
    <USED_FUNCTION>shift_u16_RA</USED_FUNCTION>
    <USED_FUNCTION>shift_16_RC</USED_FUNCTION>
    <USED_FUNCTION>shift_8_LA</USED_FUNCTION>
    <USED_FUNCTION>shift_8_LC</USED_FUNCTION>
    <USED_FUNCTION>shift_8_RA</USED_FUNCTION>
    <USED_FUNCTION>shift_u8_RA</USED_FUNCTION>
    <USED_FUNCTION>shift_8_RC</USED_FUNCTION>
  </USED_FUNCTIONS>


  <USED_FUNCTIONS name='SQRT' type='XML'>
    <USED_FUNCTION>mat_sqrt.c</USED_FUNCTION>,
    <USED_FUNCTION>matz_sqrt.c</USED_FUNCTION>
  </USED_FUNCTIONS>


  <USED_FUNCTIONS name='SUBMAT' type='XML'>
    <USED_FUNCTION>submat</USED_FUNCTION>
    <USED_FUNCTION>submatz</USED_FUNCTION>
  </USED_FUNCTIONS>

  <USED_FUNCTIONS name='SUMMATION' type='XML'>
    <USED_FUNCTION>summation</USED_FUNCTION>
    <USED_FUNCTION>summation_z</USED_FUNCTION>
    <USED_FUNCTION>summation_i32n</USED_FUNCTION>
    <USED_FUNCTION>summation_i16n</USED_FUNCTION>
    <USED_FUNCTION>summation_i8n</USED_FUNCTION>
    <USED_FUNCTION>summation_ui32n</USED_FUNCTION>
    <USED_FUNCTION>summation_ui16n</USED_FUNCTION>
    <USED_FUNCTION>summation_ui8n</USED_FUNCTION>
    <USED_FUNCTION>summation_i32s</USED_FUNCTION>
    <USED_FUNCTION>summation_i16s</USED_FUNCTION>
    <USED_FUNCTION>summation_i8s</USED_FUNCTION>
    <USED_FUNCTION>summation_ui32s</USED_FUNCTION>
    <USED_FUNCTION>summation_ui16s</USED_FUNCTION>
    <USED_FUNCTION>summation_ui8s</USED_FUNCTION>
    <USED_FUNCTION>summation_i32e</USED_FUNCTION>
    <USED_FUNCTION>summation_i16e</USED_FUNCTION>
    <USED_FUNCTION>summation_i8e</USED_FUNCTION>
    <USED_FUNCTION>summation_ui32e</USED_FUNCTION>
    <USED_FUNCTION>summation_ui16e</USED_FUNCTION>
    <USED_FUNCTION>summation_ui8e</USED_FUNCTION>
  </USED_FUNCTIONS>

  <USED_FUNCTIONS name='SWITCH2_s' type='XML'>
    <USED_FUNCTION>switch2n</USED_FUNCTION>
  </USED_FUNCTIONS>

  <USED_FUNCTIONS name='TrigFun' type='XML'>
    <USED_FUNCTION>sin_blk</USED_FUNCTION>
    <USED_FUNCTION>cos_blk</USED_FUNCTION>
    <USED_FUNCTION>tan_blk</USED_FUNCTION>
    <USED_FUNCTION>asin_blk</USED_FUNCTION>
    <USED_FUNCTION>acos_blk</USED_FUNCTION>
    <USED_FUNCTION>atan_blk</USED_FUNCTION>
    <USED_FUNCTION>sinh_blk</USED_FUNCTION>
    <USED_FUNCTION>cosh_blk</USED_FUNCTION>
    <USED_FUNCTION>tanh_blk</USED_FUNCTION>
    <USED_FUNCTION>asinh_blk</USED_FUNCTION>
    <USED_FUNCTION>acosh_blk</USED_FUNCTION>
    <USED_FUNCTION>atanh_blk</USED_FUNCTION>
  </USED_FUNCTIONS>
</DATA>
